{
  "pages": [{
    "path": "pages/index/index",
    "style": {
      "navigationBarTitleText": "",
      "enablePullDownRefresh": true

    }
  }, {
    "path": "pages/forumList/forumList",
    "style": {
      "navigationBarTitleText": ""
    }
  }, {
    "path": "pages/mine/mine",
    "style": {
      "navigationBarTitleText": "",
      "enablePullDownRefresh": true
    }
  }, {
    "path": "pages/login/login",
    "style": {}
  }, {
    "path": "pages/thread/thread",
    "style": {
      "enablePullDownRefresh": true
    }
  }, {
    "path": "pages/writeReplies/writeReplies",
    "style": {}
  }, {
    "path": "pages/forum/forum",
    "style": {
      "enablePullDownRefresh": true
    }
  }],

  "globalStyle": {
    "navigationBarTextStyle": "black",
    "navigationBarTitleText": "",
    "navigationBarBackgroundColor": "#FFFFFF",
    "navigationStyle": "custom",
    "backgroundColor": "#F8F8F8",

    "app-plus": {
      "softinputNavBar": "none"
    }
  },


  "tabBar": {
    "color": "#707070",
    "selectedColor": "#DE533A",
    "list": [{
      "pagePath": "pages/index/index",
      "text": "信息流"
    }, {
      "pagePath": "pages/forumList/forumList",
      "text": "版块"
    }, {
      "pagePath": "pages/mine/mine",
      "text": "我的"
    }]
  }
}